odoo/addons/sale_substate/README.rst
odoo/addons/sale_substate/__init__.py
odoo/addons/sale_substate/__manifest__.py
odoo/addons/sale_substate/data/sale_substate_data.xml
odoo/addons/sale_substate/data/sale_substate_demo.xml
odoo/addons/sale_substate/data/sale_substate_mail_template_data.xml
odoo/addons/sale_substate/i18n/es.po
odoo/addons/sale_substate/i18n/it.po
odoo/addons/sale_substate/i18n/sale_substate.pot
odoo/addons/sale_substate/models/__init__.py
odoo/addons/sale_substate/models/sale_order.py
odoo/addons/sale_substate/readme/CONTRIBUTORS.rst
odoo/addons/sale_substate/readme/DESCRIPTION.rst
odoo/addons/sale_substate/readme/USAGE.rst
odoo/addons/sale_substate/static/description/icon.png
odoo/addons/sale_substate/static/description/index.html
odoo/addons/sale_substate/tests/__init__.py
odoo/addons/sale_substate/tests/test_sale_substate.py
odoo/addons/sale_substate/views/sale_views.xml
odoo14_addon_sale_substate-14.0.1.0.1.dev12.dist-info/METADATA
odoo14_addon_sale_substate-14.0.1.0.1.dev12.dist-info/WHEEL
odoo14_addon_sale_substate-14.0.1.0.1.dev12.dist-info/top_level.txt
odoo14_addon_sale_substate-14.0.1.0.1.dev12.dist-info/RECORD
